allstarlist/__init__.py
allstarlist/main.py
allstarlist-0.1.0.dist-info/METADATA
allstarlist-0.1.0.dist-info/WHEEL
allstarlist-0.1.0.dist-info/entry_points.txt
allstarlist-0.1.0.dist-info/top_level.txt
allstarlist-0.1.0.dist-info/RECORD
