Metadata-Version: 2.1
Name: allstarlist
Version: 0.1.0
Summary: A Python package for allstarlist
Author: Jon Poindexter W5ALC
Author-email: w5alc@skyhublink.com
Classifier: Programming Language :: Python :: 3
Classifier: License :: OSI Approved :: MIT License
Classifier: Operating System :: OS Independent
Requires-Python: >=3.6
Requires-Dist: beautifulsoup4
Requires-Dist: tenacity
Requires-Dist: rich
Requires-Dist: requests
